nnd_app_sdk/__init__.py
nnd_app_sdk/signin/__init__.py
nnd_app_sdk/signin/base.py
nnd_app_sdk/signin/signins/__init__.py
nnd_app_sdk/signin/signins/bonfire.py
nnd_app_sdk-0.1.0.dist-info/COPYING
nnd_app_sdk-0.1.0.dist-info/COPYING.LESSER
nnd_app_sdk-0.1.0.dist-info/LICENSE
nnd_app_sdk-0.1.0.dist-info/METADATA
nnd_app_sdk-0.1.0.dist-info/WHEEL
nnd_app_sdk-0.1.0.dist-info/RECORD
